gw/conversion_factors.py
gw/data_classes/__init__.py
gw/data_classes/market_type.py
gw/enums/__init__.py
gw/enums/gw_str_enum.py
gw/enums/market_price_unit.py
gw/enums/market_quantity_unit.py
gw/enums/market_type_name.py
gw/enums/message_category.py
gw/enums/message_category_symbol.py
gw/enums/recognized_currency_unit.py
gw/errors.py
gw/named_types/__init__.py
gw/named_types/gw_base.py
gw/py.typed
gw/utils.py
gw_test/__init__.py
gw_test/py.typed
gw_test/wait.py
gridworks-1.5.7.dist-info/LICENSE
gridworks-1.5.7.dist-info/METADATA
gridworks-1.5.7.dist-info/WHEEL
gridworks-1.5.7.dist-info/RECORD
