Metadata-Version: 2.1
Name: gridworks
Version: 1.5.7
Summary: Gridworks
Home-page: https://github.com/thegridelectric/gridworks
License: MIT
Author: GridWorks
Author-email: gridworks@gridworks-consulting.com
Requires-Python: >=3.11,<4.0
Classifier: Development Status :: 3 - Alpha
Classifier: License :: OSI Approved :: MIT License
Classifier: Programming Language :: Python :: 3
Classifier: Programming Language :: Python :: 3.11
Classifier: Programming Language :: Python :: 3.12
Classifier: Programming Language :: Python :: 3.13
Requires-Dist: pydantic (>=2.8.0,<3.0.0)
Requires-Dist: python-dotenv (>=1.0.0)
Project-URL: Changelog, https://github.com/thegridelectric/gridworks/releases
Project-URL: Documentation, https://gridworks.readthedocs.io
Project-URL: Repository, https://github.com/thegridelectric/gridworks
